{
"Pruritus": 172,
"Hemorrhage": 170,
"Stroke": 169,
"Nausea": 169,
"Liver Diseases": 169,
"Myocardial Infarction": 167,
"Trichohepatoenteric Syndrome": 164,
"Gastrointestinal Hemorrhage": 161,
"Stevens-Johnson Syndrome": 160,
"Dizziness": 158,
"Urticaria": 156,
"Edema": 154,
"Headache": 154,
"Fever": 152,
"Dyspepsia": 149,
"Exanthema": 148,
"Paresthesia": 148,
"Abdominal Pain": 147,
"Drug-Related Side Effects and Adverse Reactions": 145,
"Eosinophilia": 143,
"Gastritis": 141,
"Asthma": 139,
"Anemia": 138,
"Hypertension": 137,
"Liver Failure": 137,
"Apnea": 136,
"Dermatitis, Exfoliative": 136,
"Esophageal Perforation": 135,
"Hematuria": 133,
"Pain": 128,
"Constipation": 127,
"Melena": 123,
"Pancreatitis": 123,
"Tinnitus": 120,
"Vertigo": 117,
"Renal Insufficiency": 117,
"Peptic Ulcer": 117,
"Esophageal Diseases": 116,
"Leukopenia": 116,
"Flatulence": 114,
"Proteinuria": 113,
"Angioedema": 113,
"Tachycardia": 112,
"Pneumonia": 112,
"Thrombocytopenia": 111,
"Pancytopenia": 111,
"Confusion": 110,
"Cardiovascular Diseases": 109,
"Nephritis, Interstitial": 109,
"Vasculitis": 109,
"Sleep Initiation and Maintenance Disorders": 108,
"Ulcer": 107,
"Anemia, Hemolytic": 107,
"Gastrointestinal Diseases": 106,
"Purpura": 106,
"Erythema Multiforme": 106,
"Aspirin": 105,
"Anemia, Aplastic": 103,
"Vomiting": 102,
"Xerostomia": 102,
"Diclofenac": 101,
"Syncope": 101,
"Stomatitis": 101,
"Hallucinations": 101,
"Tremor": 100,
"Heart Failure": 100,
"Dysuria": 99,
"Pyelonephritis": 98,
"Heartburn": 97,
"Bronchial Spasm": 96,
"Agranulocytosis": 96,
"Cerebellar Diseases": 95,
"Eructation": 94,
"Cystitis": 94,
"Anaphylaxis": 94,
"Hyperglycemia": 93,
"Hematemesis": 91,
"Glossitis": 90,
"Hypersensitivity": 90,
"Apraxia, oculomotor, Cogan type": 89,
"Polyuria": 88,
"Hepatitis": 88,
"Hypotension": 87,
"Meningitis": 87,
"Asthenia": 86,
"Oliguria": 86,
"Ecchymosis": 86,
"Inflammation": 84,
"AIDS-Related Complex": 82,
"Fatigue": 82,
"Rhinitis": 81,
"Colitis": 81,
"Conjunctivitis": 78,
"Osteoarthritis": 76,
"Arrhythmias, Cardiac": 73,
"Sepsis": 72,
"Kidney Diseases": 72,
"Seizures": 70,
"Arthritis, Rheumatoid": 69,
"Respiratory Insufficiency": 69,
"Nasal Polyps": 66,
"Acute Kidney Injury": 64,
"Prostaglandins": 63,
"Hyperkalemia": 63,
"Hearing Disorders": 62,
"Osteochondrodysplasias": 62,
"Thiazides": 62,
"Sinusitis": 60,
"Disorders of Excessive Somnolence": 59,
"Mastocytoma, Skin": 58,
"Dehydration": 56,
"Pharyngitis": 56,
"Blood Coagulation Disorders": 55,
"Myalgia": 54,
"Dermatitis": 54,
"Wounds and Injuries": 51,
"Lethargy": 51,
"Anorexia Nervosa": 49,
"Adrenal Cortex Hormones": 47,
"Kidney Calculi": 45,
"Epistaxis": 45,
"Arthralgia": 44,
"Stomatitis, Aphthous": 44,
"Muscle Hypertonia": 43,
"Gastroenteritis": 41,
"Arthritis": 41,
"Chest Pain": 40,
"Deglutition Disorders": 38,
"Deafness": 38,
"Myocardial Ischemia": 38,
"Fanconi Syndrome": 38,
"Food Hypersensitivity": 38,
"Uterine Hemorrhage": 38,
"Migraine Disorders": 37,
"Hypovolemia": 37,
"Warfarin": 37,
"Laryngitis": 36,
"Bronchitis": 35,
"Erythema": 35,
"Stomach Ulcer": 34,
"Fetal Death": 34,
"Hypoaldosteronism": 34,
"Intestinal Perforation": 34,
"Hypercholesterolemia": 32,
"Leukorrhea": 32,
"Dysmenorrhea": 31,
"Esophageal Achalasia": 30,
"Thrombocytosis": 30,
"Meningitis, Aseptic": 29,
"Ductus Arteriosus, Patent": 29,
"Hypesthesia": 29,
"Cataract": 28,
"Gastroesophageal Reflux": 28,
"Hypokalemia": 27,
"Constriction, Pathologic": 27,
"Pulmonary Embolism": 27,
"Hemorrhoids": 27,
"Dystocia": 26,
"Hepatic Insufficiency": 26,
"Nephritis": 26,
"Coronary Artery Disease": 26,
"Infarction": 26,
"Intracranial Hemorrhages": 26,
"Diplopia": 25,
"Acetaminophen": 25,
"Etodolac": 25,
"Duodenitis": 25,
"Neutropenia": 25,
"Hyperpigmentation": 25,
"Chemical and Drug Induced Liver Injury": 25,
"Hernia, Hiatal": 25,
"Respiratory Tract Infections": 24,
"Jaundice, Obstructive": 24,
"Thrombophlebitis": 24,
"Skin Manifestations": 23,
"Eczema": 23,
"Skin Diseases": 23,
"Arthritis, Juvenile": 23,
"Nephrotic Syndrome": 22,
"Amblyopia": 22,
"Ileus": 22,
"Influenza, Human": 21,
"Cough": 21,
"Olfaction Disorders": 21,
"Nasopharyngitis": 21,
"Eye Pain": 20,
"Ventricular Fibrillation": 20,
"Hyponatremia": 20,
"Adenomatous Polyposis Coli": 20,
"Colorectal Neoplasms, Hereditary Nonpolyposis": 20,
"Sulfonamides": 20,
"Diverticulitis": 20,
"Synovitis": 20,
"Tendinopathy": 20,
"Venous Thrombosis": 20,
"Uveitis": 20,
"Spondylitis, Ankylosing": 20,
"Dry Socket": 20,
"Polyps": 20,
"Adenomatous Polyps": 20,
"Menorrhagia": 19,
"Acne Vulgaris": 19,
"Ageusia": 19,
"Death, Sudden": 19,
"Iritis": 18,
"Oral Ulcer": 18,
"Neuralgia": 18,
"Vasculitis, Leukocytoclastic, Cutaneous": 18,
"Tuberculosis, Cardiovascular": 18,
"Chronic Disease": 18,
"Testosterone": 18,
"Cysts": 17,
"Neurobehavioral Manifestations": 16,
"Dermatitis, Contact": 16,
"Nocturia": 16,
"Chills": 16,
"Hyperemia": 16,
"Aortic Valve Insufficiency": 16,
"Menstruation Disturbances": 15,
"Indomethacin": 15,
"Photophobia": 15,
"Misoprostol": 15,
"Hematoma": 15,
"Syndrome": 14,
"Cholelithiasis": 14,
"Epilepsy": 14,
"Foreign-Body Reaction": 14,
"Noninflammatory corneal thinning": 13,
"Corneal Perforation": 13,
"Urinary Tract Infections": 13,
"Muscle Cramp": 13,
"Lacrimal Apparatus Diseases": 13,
"Hyperuricemia": 13,
"Necrosis": 13,
"Infections": 13,
"Skin Neoplasms": 13,
"Drug Hypersensitivity Syndrome": 13,
"Eye Diseases": 13,
"Keratitis": 12,
"Corneal Ulcer": 12,
"Metrorrhagia": 12,
"Pulmonary Edema": 12,
"Optic Neuritis": 12,
"Acidosis": 12,
"Azotemia": 12,
"Glycosuria": 12,
"Back Pain": 12,
"Shock": 11,
"Urinary Incontinence": 11,
"Skin Ulcer": 11,
"Asthma, Aspirin-Induced": 11,
"Dilatation, Pathologic": 11,
"Inflammatory Bowel Diseases": 11,
"Hyperventilation": 11,
"Night Blindness": 11,
"Osteoarthritis, Knee": 11,
"Sleep-Wake Transition Disorders": 11,
"Urinary Retention": 10,
"Corneal Edema": 10,
"Asthenopia": 10,
"Cellulitis": 10,
"Albuminuria": 10,
"Thrombosis": 10,
"Corneal Opacity": 10,
"Crohn Disease": 10,
"Erectile Dysfunction": 10,
"Fasciitis, Necrotizing": 10,
"Hyphema": 9,
"Vaginitis": 9,
"Lung Diseases": 9,
"Malignant Carcinoid Syndrome": 9,
"Staphylococcal Scalded Skin Syndrome": 9,
"Duodenal Ulcer": 9,
"Ventricular Premature Complexes": 9,
"Hyperesthesia": 9,
"Hyperbilirubinemia, Hereditary": 9,
"Blood Loss, Surgical": 9,
"Breast Diseases": 9,
"Steroids": 8,
"Dry Eye Syndromes": 8,
"Learning Disabilities": 8,
"Muscle Weakness": 8,
"Epidermolysis Bullosa": 8,
"Spasm": 8,
"Ataxia": 8,
"Caffeine": 8,
"Virus Diseases": 8,
"Reye Syndrome": 8,
"Attention Deficit Disorder with Hyperactivity": 8,
"Glaucoma": 8,
"Hot Flashes": 8,
"Acute Generalized Exanthematous Pustulosis": 8,
"Laryngeal Edema": 8,
"Acute Pain": 8,
"Halitosis": 8,
"Neck Pain": 8,
"Laryngismus": 8,
"Disease Progression": 8,
"Carcinoma": 7,
"Gingivitis, Necrotizing Ulcerative": 7,
"Dermatitis, Phototoxic": 7,
"Benzodiazepines": 7,
"Neonatal Abstinence Syndrome": 7,
"Adrenal Insufficiency": 7,
"Androgens": 7,
"Hypoglycemia": 7,
"Tachycardia, Sinus": 7,
"Pediatric ulcerative colitis": 7,
"Phlebitis": 7,
"Leukocytosis": 7,
"Chondrocalcinosis 2": 7,
"Porphyrias": 7,
"Paranoid Disorders": 7,
"Pruritus Ani": 7,
"Cholestasis": 7,
"Retrograde Degeneration": 7,
"Disseminated Intravascular Coagulation": 7,
"Intestinal Obstruction": 7,
"phenylacetic acid": 6,
"phenyl acetate": 6,
"Cholecystitis": 6,
"Periodontal Abscess": 6,
"Prostatic Diseases": 6,
"Amnesia": 6,
"Hematoma, Subdural": 6,
"Herpes Simplex": 6,
"Herpes Zoster": 6,
"Nail Diseases": 6,
"Ear Diseases": 6,
"Respiratory Distress Syndrome, Newborn": 6,
"Obesity": 6,
"Subarachnoid Hemorrhage": 6,
"Hiccup": 6,
"Infant, Newborn, Diseases": 6,
"Vitamin K Deficiency": 6,
"Gastroparesis": 6,
"Periodontal Atrophy": 6,
"Mastodynia": 6,
"Pemphigoid, Bullous": 6,
"Dysgeusia": 6,
"Diflunisal": 6,
"Atrial Fibrillation": 6,
"Ketorolac Tromethamine": 5,
"Corneal Diseases": 5,
"Restless Legs Syndrome": 5,
"Rectal Diseases": 5,
"Tooth Diseases": 5,
"Nephrosclerosis": 5,
"Pyuria": 5,
"Ulnar Neuropathies": 5,
"Paralysis": 5,
"Scleritis": 5,
"Keratoconjunctivitis": 5,
"Respiration Disorders": 5,
"Bone Diseases": 5,
"Fractures, Bone": 5,
"Prolapse": 5,
"Bursitis": 5,
"Glycosuria, Renal": 5,
"Alkalosis": 5,
"Ischemic Attack, Transient": 5,
"Vision Disorders": 5,
"Angina, Unstable": 5,
"Esophageal Spasm, Diffuse": 5,
"Substance-Related Disorders": 5,
"Mental Disorders": 5,
"Hypoventilation": 5,
"Hypotension, Orthostatic": 5,
"Pseudotumor Cerebri": 5,
"Colic": 5,
"Gastrointestinal Neoplasms": 5,
"Taste Disorders": 5,
"Malocclusion, Angle Class II": 5,
"Psoriasis": 5,
"Alkalosis, Respiratory": 5,
"Nutritional and Metabolic Diseases": 4,
"Hoarseness": 4,
"Pulmonary Heart Disease": 4,
"Brain Neoplasms": 4,
"Craniocerebral Trauma": 4,
"Depressive Disorder, Major": 4,
"Barbiturates": 4,
"Carbon Dioxide": 4,
"Hypoxia": 4,
"Sleep Apnea, Obstructive": 4,
"Neuromuscular Diseases": 4,
"Tylosin": 4,
"Erythromycin": 4,
"Ritonavir": 4,
"Rifampin": 4,
"Carbamazepine": 4,
"Phenytoin": 4,
"norcodeine": 4,
"Amiodarone": 4,
"Pulmonary Disease, Chronic Obstructive": 4,
"Hypercapnia": 4,
"Phenothiazines": 4,
"Intestinal Pseudo-Obstruction": 4,
"Biliary Tract Diseases": 4,
"Pentazocine": 4,
"Nalbuphine": 4,
"Buprenorphine": 4,
"Genetic Diseases, Inborn": 4,
"Hemophilia A": 4,
"Drug Hypersensitivity": 4,
"Hydroxyindoleacetic Acid": 4,
"Vanilmandelic Acid": 4,
"Psychomotor Agitation": 4,
"Hyperhidrosis": 4,
"Earache": 4,
"Iron-Dextran Complex": 4,
"diclofenac hydroxyethylpyrrolidine": 4,
"Hydrocodone": 4,
"Vascular Diseases": 4,
"Endocrine System Diseases": 4,
"Blackwater Fever": 4,
"Lichen Planus": 4,
"Acro-Osteolysis": 4,
"Diverticulum": 4,
"Gynecomastia": 4,
"Leukemia": 4,
"Myoclonus": 4,
"Dermatitis, Seborrheic": 4,
"Hepatorenal Syndrome": 4,
"Memory Disorders": 4,
"Tic Disorders": 4,
"Ocular Motility Disorders": 4,
"Scotoma": 4,
"Bundle-Branch Block": 4,
"Adenomyosis": 4,
"Premature Birth": 4,
"Cerebral Infarction": 4,
"Pituitary Diseases": 4,
"Peripheral Nervous System Diseases": 4,
"Hypothermia": 4,
"Brain Edema": 4,
"Eye Infections": 3,
"Breast Neoplasms": 3,
"Alcoholism": 3,
"Sleep Apnea, Central": 3,
"Anemia, Iron-Deficiency": 3,
"Disease": 3,
"Nervous System Diseases": 3,
"Lupus Erythematosus, Systemic": 3,
"Porphyria Cutanea Tarda": 3,
"Blister": 3,
"Papilledema": 3,
"Infertility": 3,
"Stomach Diseases": 3,
"Pulmonary Eosinophilia": 3,
"Melkersson-Rosenthal Syndrome": 3,
"Weight Loss": 3,
"Glomerulonephritis, Membranous": 3,
"Johnson neuroectodermal syndrome": 3,
"Labyrinthitis": 3,
"Tennis Elbow": 3,
"Bradycardia": 3,
"Respiratory Sounds": 3,
"Dipyridamole": 3,
"Brain Ischemia": 3,
"Hemoptysis": 3,
"Rhabdomyolysis": 3,
"Tachypnea": 3,
"Esophagitis": 3,
"Congenital Abnormalities": 3,
"Tuberculosis, Osteoarticular": 2,
"Hydrarthrosis": 2,
"Cholestasis with Gallstone, Ataxia, and Visual Disturbance": 2,
"Coronary Vasospasm": 2,
"Angina Pectoris, Variant": 2,
"Wolff-Parkinson-White Syndrome": 2,
"Cerebrovascular Disorders": 2,
"Splenic Infarction": 2,
"Raynaud Disease": 2,
"Blindness": 2,
"Cluster Headache": 2,
"Multiple Organ Failure": 2,
"Ergotamine": 2,
"Tryptamines": 2,
"Headache Disorders, Secondary": 2,
"Headache Disorders": 2,
"Panic Disorder": 2,
"Reflex, Abnormal": 2,
"Exsanguination": 2,
"Airway Obstruction": 2,
"Psychotic Disorders": 2,
"Cholangiocarcinoma": 2,
"Flurbiprofen": 2,
"Fibrosis": 2,
"Miosis": 2,
"Mydriasis": 2,
"Vision, Low": 2,
"Erythema Nodosum": 2,
"Arthrotec": 2,
"Triamterene": 2,
"Parkinsonian Disorders": 2,
"Ileitis": 2,
"Athetosis": 2,
"Glioblastoma": 2,
"Flushing": 2,
"Neoplasms": 2,
"Exfoliation Syndrome": 2,
"Common Cold": 2,
"Ovarian Cysts": 2,
"Bites and Stings": 2,
"Tooth Discoloration": 2,
"sodium sulfite": 2,
"Acquired angioedema": 2,
"Teratogenesis": 2,
"Spinal Dysraphism": 2,
"Microphthalmos": 2,
"Craniosynostoses": 2,
"Skin Abnormalities": 2,
"Fetal Resorption": 2,
"Anemia, Sickle Cell": 2,
"Cerebral Hemorrhage": 2,
"Foreign Bodies": 2,
"Pemphigoid, Benign Mucous Membrane": 2,
"Nephrosis": 2,
"Osteoarthritis, Hip": 1,
"4'-hydroxyflurbiprofen": 1,
"Ischemia": 1,
"Pulmonary Infarction": 1,
"Retinal Hemorrhage": 1,
"Vulvovaginitis": 1,
"Heart Injuries": 1,
"Megacolon, Toxic": 1,
"Purpura, Thrombotic Thrombocytopenic": 1,
"Thienopyridines": 1,
"Factor 8 deficiency, acquired": 1,
"Colitis, Lymphocytic": 1,
"Serum Sickness": 1,
"Lung Diseases, Interstitial": 1,
"Skin Diseases, Vesiculobullous": 1,
"Urinary Incontinence, Urge": 1,
"Mouth Diseases": 1,
"Uterine Rupture": 1,
"Embolism, Amniotic Fluid": 1,
"Nutrition Disorders": 1,
"Hypertrophy": 1,
"Retinopathy of Prematurity": 1,
"Catamenial pneumothorax": 1,
"Uremia": 1,
"Hypertension, Pulmonary": 1,
"Enterocolitis, Necrotizing": 1,
"Shoulder Pain": 1,
"Arthritis, Gouty": 1,
"Parapsoriasis": 1,
"Meniere Disease": 1,
"Urolithiasis": 1,
"Aspartame": 1,
"Ocular Hypertension": 1,
"Mouth Breathing": 1,
"Ketones": 1,
"Streptococcal Infections": 1,
"Reticulocytosis": 1,
"Patent Ductus Venosus": 1,
"Carcinoma, Skin Appendage": 1,
"Branchio-Oto-Renal Syndrome": 1,
"Calculi": 1,
"Somatoform Disorders": 1,
"Hemorrhagic Disorders": 1,
"Conjunctivitis, Allergic": 1,
"Lidocaine": 1,
"Unconsciousness": 1,
"Heart Arrest": 1,
"Bahemuka Brown syndrome": 1,
"methylparaben": 1,
"Headache Disorders, Primary": 1,
"Fallopian Tube Diseases": 1,
"Sexual Dysfunctions, Psychological": 1,
"Autonomic Dysreflexia": 1,
"Coronary Aneurysm": 1,
"Nephrosis, Lipoid": 1,
"anagrelide": 1,
"Central Nervous System Diseases": 1,
"Chronobiology Disorders": 1,
"Phenylketonurias": 1,
"Fetal Diseases": 1,
"Ichthyosis, Lamellar": 1,
"Onycholysis": 1,
"Anuria": 1,
"Trigeminal Neuralgia": 1
}