<?xml version="1.0" encoding="UTF-8"?><?xml-stylesheet href="http://www.accessdata.fda.gov/spl/stylesheet/spl.xsl" type="text/xsl"?>
<document xmlns:xsi="http://www.w3.org/2001/XMLSchema-instance" xmlns="urn:hl7-org:v3" xsi:schemaLocation="urn:hl7-org:v3 http://www.accessdata.fda.gov/spl/schema/spl.xsd">
   <id root="5bd8cf4a-096a-5a2a-e053-2a91aa0ad499"/>
   <code code="34390-5" codeSystem="2.16.840.1.113883.6.1" displayName="HUMAN OTC DRUG LABEL"/>
   <title>Ibuprofen Caplets, USP 200 mg</title>
   <effectiveTime value="20171018"/>
   <setId root="e7c6d352-a460-4bf8-a92f-5865249bd22b"/>
   <versionNumber value="8"/>
   <author>
      <time/>
      <assignedEntity>
         <representedOrganization>
            <id root="1.3.6.1.4.1.519.1" extension="079674526"/>
            <name>AiPing Pharmaceutical, Inc.</name>
            <assignedEntity>
               <assignedOrganization>
                  <id root="1.3.6.1.4.1.519.1" extension="079674526"/>
                  <name>AiPing Pharmaceutical, Inc.</name>
                  <assignedEntity>
                     <assignedOrganization>
                        <id root="1.3.6.1.4.1.519.1" extension="528101821"/>
                        <name>Anshi Pharmaceutical (Zhongshan) Inc.</name>
                     </assignedOrganization>
                     <performance>
                        <actDefinition>
                           <code code="C43360" displayName="manufacture" codeSystem="2.16.840.1.113883.3.26.1.1"/>
                           <product>
                              <manufacturedProduct classCode="MANU">
                                 <manufacturedMaterialKind>
                                    <code code="11788-003" codeSystem="2.16.840.1.113883.6.69"/>
                                 </manufacturedMaterialKind>
                              </manufacturedProduct>
                           </product>
                        </actDefinition>
                     </performance>
                     <performance>
                        <actDefinition>
                           <code code="C43360" displayName="manufacture" codeSystem="2.16.840.1.113883.3.26.1.1"/>
                           <product>
                              <manufacturedProduct classCode="MANU">
                                 <manufacturedMaterialKind>
                                    <code code="11788-005" codeSystem="2.16.840.1.113883.6.69"/>
                                 </manufacturedMaterialKind>
                              </manufacturedProduct>
                           </product>
                        </actDefinition>
                     </performance>
                     <performance>
                        <actDefinition>
                           <code code="C43360" displayName="manufacture" codeSystem="2.16.840.1.113883.3.26.1.1"/>
                           <product>
                              <manufacturedProduct classCode="MANU">
                                 <manufacturedMaterialKind>
                                    <code code="11788-007" codeSystem="2.16.840.1.113883.6.69"/>
                                 </manufacturedMaterialKind>
                              </manufacturedProduct>
                           </product>
                        </actDefinition>
                     </performance>
                  </assignedEntity>
               </assignedOrganization>
            </assignedEntity>
         </representedOrganization>
      </assignedEntity>
   </author>
   <component>
      <structuredBody>
         <component>
            <section>
               <id root="5bdb5059-2f2d-095a-e053-2a91aa0accd5"/>
               <code code="48780-1" codeSystem="2.16.840.1.113883.6.1" displayName="SPL product data elements section"/>
               <effectiveTime value="20171018"/>
               <subject>
                  <manufacturedProduct>
                     <manufacturedProduct>
                        <code code="11788-003" codeSystem="2.16.840.1.113883.6.69"/>
                        <name>Ibuprofen</name>
                        <formCode code="C42931" codeSystem="2.16.840.1.113883.3.26.1.1" displayName="TABLET, FILM COATED"/>
                        <asEntityWithGeneric>
                           <genericMedicine>
                              <name>Ibuprofen</name>
                           </genericMedicine>
                        </asEntityWithGeneric>
                        <ingredient classCode="IACT">
                           <ingredientSubstance>
                              <code code="ETJ7Z6XBU4" codeSystem="2.16.840.1.113883.4.9"/>
                              <name>SILICON DIOXIDE</name>
                           </ingredientSubstance>
                        </ingredient>
                        <ingredient classCode="IACT">
                           <ingredientSubstance>
                              <code code="M28OL1HH48" codeSystem="2.16.840.1.113883.4.9"/>
                              <name>CROSCARMELLOSE SODIUM</name>
                           </ingredientSubstance>
                        </ingredient>
                        <ingredient classCode="IACT">
                           <ingredientSubstance>
                              <code code="35SW5USQ3G" codeSystem="2.16.840.1.113883.4.9"/>
                              <name>D&amp;C YELLOW NO. 10</name>
                           </ingredientSubstance>
                        </ingredient>
                        <ingredient classCode="IACT">
                           <ingredientSubstance>
                              <code code="L06K8R7DQK" codeSystem="2.16.840.1.113883.4.9"/>
                              <name>FD&amp;C BLUE NO. 2</name>
                           </ingredientSubstance>
                        </ingredient>
                        <ingredient classCode="IACT">
                           <ingredientSubstance>
                              <code code="H77VEI93A8" codeSystem="2.16.840.1.113883.4.9"/>
                              <name>FD&amp;C YELLOW NO. 6</name>
                           </ingredientSubstance>
                        </ingredient>
                        <ingredient classCode="IACT">
                           <ingredientSubstance>
                              <code code="1DI56QDM62" codeSystem="2.16.840.1.113883.4.9"/>
                              <name>LECITHIN, SOYBEAN</name>
                           </ingredientSubstance>
                        </ingredient>
                        <ingredient classCode="IACT">
                           <ingredientSubstance>
                              <code code="70097M6I30" codeSystem="2.16.840.1.113883.4.9"/>
                              <name>MAGNESIUM STEARATE</name>
                           </ingredientSubstance>
                        </ingredient>
                        <ingredient classCode="IACT">
                           <ingredientSubstance>
                              <code code="OP1R32D61U" codeSystem="2.16.840.1.113883.4.9"/>
                              <name>CELLULOSE, MICROCRYSTALLINE</name>
                           </ingredientSubstance>
                        </ingredient>
                        <ingredient classCode="IACT">
                           <ingredientSubstance>
                              <code code="4R4HFI6D95" codeSystem="2.16.840.1.113883.4.9"/>
                              <name>POLYETHYLENE GLYCOL 4000</name>
                           </ingredientSubstance>
                        </ingredient>
                        <ingredient classCode="IACT">
                           <ingredientSubstance>
                              <code code="532B59J990" codeSystem="2.16.840.1.113883.4.9"/>
                              <name>POLYVINYL ALCOHOL</name>
                           </ingredientSubstance>
                        </ingredient>
                        <ingredient classCode="IACT">
                           <ingredientSubstance>
                              <code code="O8232NY3SJ" codeSystem="2.16.840.1.113883.4.9"/>
                              <name>STARCH, PREGELATINIZED CORN</name>
                           </ingredientSubstance>
                        </ingredient>
                        <ingredient classCode="IACT">
                           <ingredientSubstance>
                              <code code="7SEV7J4R1U" codeSystem="2.16.840.1.113883.4.9"/>
                              <name>TALC</name>
                           </ingredientSubstance>
                        </ingredient>
                        <ingredient classCode="IACT">
                           <ingredientSubstance>
                              <code code="15FIX9V2JP" codeSystem="2.16.840.1.113883.4.9"/>
                              <name>TITANIUM DIOXIDE</name>
                           </ingredientSubstance>
                        </ingredient>
                        <ingredient classCode="ACTIB">
                           <quantity>
                              <numerator unit="mg" value="200"/>
                              <denominator unit="1" value="1"/>
                           </quantity>
                           <ingredientSubstance>
                              <code code="WK2XYI10QM" codeSystem="2.16.840.1.113883.4.9"/>
                              <name>IBUPROFEN</name>
                              <activeMoiety>
                                 <activeMoiety>
                                    <code code="WK2XYI10QM" codeSystem="2.16.840.1.113883.4.9"/>
                                    <name>IBUPROFEN</name>
                                 </activeMoiety>
                              </activeMoiety>
                           </ingredientSubstance>
                        </ingredient>
                        <asContent>
                           <quantity>
                              <numerator value="24" unit="1"/>
                              <denominator value="1"/>
                           </quantity>
                           <containerPackagedProduct>
                              <code/>
                              <formCode code="C43169" codeSystem="2.16.840.1.113883.3.26.1.1" displayName="BOTTLE"/>
                              <asContent>
                                 <quantity>
                                    <numerator value="1" unit="1"/>
                                    <denominator value="1"/>
                                 </quantity>
                                 <containerPackagedProduct>
                                    <code code="11788-003-07" codeSystem="2.16.840.1.113883.6.69"/>
                                    <formCode code="C43182" codeSystem="2.16.840.1.113883.3.26.1.1" displayName="CARTON"/>
                                 </containerPackagedProduct>
                                 <subjectOf>
                                    <marketingAct>
                                       <code code="C53292" codeSystem="2.16.840.1.113883.3.26.1.1"/>
                                       <statusCode code="active"/>
                                       <effectiveTime>
                                          <low value="20170508"/>
                                       </effectiveTime>
                                    </marketingAct>
                                 </subjectOf>
                              </asContent>
                           </containerPackagedProduct>
                           <subjectOf>
                              <characteristic>
                                 <code code="SPLCMBPRDTP" codeSystem="2.16.840.1.113883.1.11.19255"/>
                                 <value code="C112160" codeSystem="2.16.840.1.113883.3.26.1.1" displayName="Type 0: Not a Combination Product" xsi:type="CV"/>
                              </characteristic>
                           </subjectOf>
                        </asContent>
                        <asContent>
                           <quantity>
                              <numerator value="1000" unit="1"/>
                              <denominator value="1"/>
                           </quantity>
                           <containerPackagedProduct>
                              <code code="11788-003-10" codeSystem="2.16.840.1.113883.6.69"/>
                              <formCode code="C43169" codeSystem="2.16.840.1.113883.3.26.1.1" displayName="BOTTLE"/>
                           </containerPackagedProduct>
                           <subjectOf>
                              <characteristic>
                                 <code code="SPLCMBPRDTP" codeSystem="2.16.840.1.113883.1.11.19255"/>
                                 <value code="C112160" codeSystem="2.16.840.1.113883.3.26.1.1" displayName="Type 0: Not a Combination Product" xsi:type="CV"/>
                              </characteristic>
                           </subjectOf>
                           <subjectOf>
                              <marketingAct>
                                 <code code="C53292" codeSystem="2.16.840.1.113883.3.26.1.1"/>
                                 <statusCode code="active"/>
                                 <effectiveTime>
                                    <low value="20170508"/>
                                 </effectiveTime>
                              </marketingAct>
                           </subjectOf>
                        </asContent>
                     </manufacturedProduct>
                     <subjectOf>
                        <approval>
                           <id extension="ANDA207095" root="2.16.840.1.113883.3.150"/>
                           <code code="C73584" codeSystem="2.16.840.1.113883.3.26.1.1" displayName="ANDA"/>
                           <author>
                              <territorialAuthority>
                                 <territory>
                                    <code code="USA" codeSystem="2.16.840.1.113883.5.28"/>
                                 </territory>
                              </territorialAuthority>
                           </author>
                        </approval>
                     </subjectOf>
                     <subjectOf>
                        <marketingAct>
                           <code code="C53292" codeSystem="2.16.840.1.113883.3.26.1.1"/>
                           <statusCode code="active"/>
                           <effectiveTime>
                              <low value="20170508"/>
                           </effectiveTime>
                        </marketingAct>
                     </subjectOf>
                     <subjectOf>
                        <characteristic classCode="OBS">
                           <code code="SPLCOLOR" codeSystem="2.16.840.1.113883.1.11.19255"/>
                           <value code="C48331" codeSystem="2.16.840.1.113883.3.26.1.1" displayName="orange" xsi:type="CE">
                              <originalText/>
                           </value>
                        </characteristic>
                     </subjectOf>
                     <subjectOf>
                        <characteristic classCode="OBS">
                           <code code="SPLSHAPE" codeSystem="2.16.840.1.113883.1.11.19255"/>
                           <value code="C48336" codeSystem="2.16.840.1.113883.3.26.1.1" displayName="CAPSULE" xsi:type="CE">
                              <originalText/>
                           </value>
                        </characteristic>
                     </subjectOf>
                     <subjectOf>
                        <characteristic classCode="OBS">
                           <code code="SPLSIZE" codeSystem="2.16.840.1.113883.1.11.19255"/>
                           <value unit="mm" value="15" xsi:type="PQ"/>
                        </characteristic>
                     </subjectOf>
                     <subjectOf>
                        <characteristic classCode="OBS">
                           <code code="SPLSCORE" codeSystem="2.16.840.1.113883.1.11.19255"/>
                           <value value="1" xsi:type="INT"/>
                        </characteristic>
                     </subjectOf>
                     <subjectOf>
                        <characteristic classCode="OBS">
                           <code code="SPLIMPRINT" codeSystem="2.16.840.1.113883.1.11.19255"/>
                           <value xsi:type="ST">BI;03</value>
                        </characteristic>
                     </subjectOf>
                     <consumedIn>
                        <substanceAdministration>
                           <routeCode code="C38288" codeSystem="2.16.840.1.113883.3.26.1.1" displayName="ORAL"/>
                        </substanceAdministration>
                     </consumedIn>
                  </manufacturedProduct>
               </subject>
               <subject>
                  <manufacturedProduct>
                     <manufacturedProduct>
                        <code code="11788-005" codeSystem="2.16.840.1.113883.6.69"/>
                        <name>Ibuprofen</name>
                        <formCode code="C42931" codeSystem="2.16.840.1.113883.3.26.1.1" displayName="TABLET, FILM COATED"/>
                        <asEntityWithGeneric>
                           <genericMedicine>
                              <name>Ibuprofen</name>
                           </genericMedicine>
                        </asEntityWithGeneric>
                        <ingredient classCode="IACT">
                           <ingredientSubstance>
                              <code code="ETJ7Z6XBU4" codeSystem="2.16.840.1.113883.4.9"/>
                              <name>SILICON DIOXIDE</name>
                           </ingredientSubstance>
                        </ingredient>
                        <ingredient classCode="IACT">
                           <ingredientSubstance>
                              <code code="M28OL1HH48" codeSystem="2.16.840.1.113883.4.9"/>
                              <name>CROSCARMELLOSE SODIUM</name>
                           </ingredientSubstance>
                        </ingredient>
                        <ingredient classCode="IACT">
                           <ingredientSubstance>
                              <code code="1DI56QDM62" codeSystem="2.16.840.1.113883.4.9"/>
                              <name>LECITHIN, SOYBEAN</name>
                           </ingredientSubstance>
                        </ingredient>
                        <ingredient classCode="IACT">
                           <ingredientSubstance>
                              <code code="70097M6I30" codeSystem="2.16.840.1.113883.4.9"/>
                              <name>MAGNESIUM STEARATE</name>
                           </ingredientSubstance>
                        </ingredient>
                        <ingredient classCode="IACT">
                           <ingredientSubstance>
                              <code code="OP1R32D61U" codeSystem="2.16.840.1.113883.4.9"/>
                              <name>CELLULOSE, MICROCRYSTALLINE</name>
                           </ingredientSubstance>
                        </ingredient>
                        <ingredient classCode="IACT">
                           <ingredientSubstance>
                              <code code="4R4HFI6D95" codeSystem="2.16.840.1.113883.4.9"/>
                              <name>POLYETHYLENE GLYCOL 4000</name>
                           </ingredientSubstance>
                        </ingredient>
                        <ingredient classCode="IACT">
                           <ingredientSubstance>
                              <code code="532B59J990" codeSystem="2.16.840.1.113883.4.9"/>
                              <name>POLYVINYL ALCOHOL</name>
                           </ingredientSubstance>
                        </ingredient>
                        <ingredient classCode="IACT">
                           <ingredientSubstance>
                              <code code="O8232NY3SJ" codeSystem="2.16.840.1.113883.4.9"/>
                              <name>STARCH, PREGELATINIZED CORN</name>
                           </ingredientSubstance>
                        </ingredient>
                        <ingredient classCode="IACT">
                           <ingredientSubstance>
                              <code code="7SEV7J4R1U" codeSystem="2.16.840.1.113883.4.9"/>
                              <name>TALC</name>
                           </ingredientSubstance>
                        </ingredient>
                        <ingredient classCode="IACT">
                           <ingredientSubstance>
                              <code code="15FIX9V2JP" codeSystem="2.16.840.1.113883.4.9"/>
                              <name>TITANIUM DIOXIDE</name>
                           </ingredientSubstance>
                        </ingredient>
                        <ingredient classCode="ACTIB">
                           <quantity>
                              <numerator unit="mg" value="200"/>
                              <denominator unit="1" value="1"/>
                           </quantity>
                           <ingredientSubstance>
                              <code code="WK2XYI10QM" codeSystem="2.16.840.1.113883.4.9"/>
                              <name>IBUPROFEN</name>
                              <activeMoiety>
                                 <activeMoiety>
                                    <code code="WK2XYI10QM" codeSystem="2.16.840.1.113883.4.9"/>
                                    <name>IBUPROFEN</name>
                                 </activeMoiety>
                              </activeMoiety>
                           </ingredientSubstance>
                        </ingredient>
                        <asContent>
                           <quantity>
                              <numerator value="24" unit="1"/>
                              <denominator value="1"/>
                           </quantity>
                           <containerPackagedProduct>
                              <code/>
                              <formCode code="C43169" codeSystem="2.16.840.1.113883.3.26.1.1" displayName="BOTTLE"/>
                              <asContent>
                                 <quantity>
                                    <numerator value="1" unit="1"/>
                                    <denominator value="1"/>
                                 </quantity>
                                 <containerPackagedProduct>
                                    <code code="11788-005-07" codeSystem="2.16.840.1.113883.6.69"/>
                                    <formCode code="C43182" codeSystem="2.16.840.1.113883.3.26.1.1" displayName="CARTON"/>
                                 </containerPackagedProduct>
                                 <subjectOf>
                                    <marketingAct>
                                       <code code="C53292" codeSystem="2.16.840.1.113883.3.26.1.1"/>
                                       <statusCode code="active"/>
                                       <effectiveTime>
                                          <low value="20170508"/>
                                       </effectiveTime>
                                    </marketingAct>
                                 </subjectOf>
                              </asContent>
                           </containerPackagedProduct>
                           <subjectOf>
                              <characteristic>
                                 <code code="SPLCMBPRDTP" codeSystem="2.16.840.1.113883.1.11.19255"/>
                                 <value code="C112160" codeSystem="2.16.840.1.113883.3.26.1.1" displayName="Type 0: Not a Combination Product" xsi:type="CV"/>
                              </characteristic>
                           </subjectOf>
                        </asContent>
                        <asContent>
                           <quantity>
                              <numerator value="1000" unit="1"/>
                              <denominator value="1"/>
                           </quantity>
                           <containerPackagedProduct>
                              <code code="11788-005-10" codeSystem="2.16.840.1.113883.6.69"/>
                              <formCode code="C43169" codeSystem="2.16.840.1.113883.3.26.1.1" displayName="BOTTLE"/>
                           </containerPackagedProduct>
                           <subjectOf>
                              <characteristic>
                                 <code code="SPLCMBPRDTP" codeSystem="2.16.840.1.113883.1.11.19255"/>
                                 <value code="C112160" codeSystem="2.16.840.1.113883.3.26.1.1" displayName="Type 0: Not a Combination Product" xsi:type="CV"/>
                              </characteristic>
                           </subjectOf>
                           <subjectOf>
                              <marketingAct>
                                 <code code="C53292" codeSystem="2.16.840.1.113883.3.26.1.1"/>
                                 <statusCode code="active"/>
                                 <effectiveTime>
                                    <low value="20170508"/>
                                 </effectiveTime>
                              </marketingAct>
                           </subjectOf>
                        </asContent>
                     </manufacturedProduct>
                     <subjectOf>
                        <approval>
                           <id extension="ANDA207095" root="2.16.840.1.113883.3.150"/>
                           <code code="C73584" codeSystem="2.16.840.1.113883.3.26.1.1" displayName="ANDA"/>
                           <author>
                              <territorialAuthority>
                                 <territory>
                                    <code code="USA" codeSystem="2.16.840.1.113883.5.28"/>
                                 </territory>
                              </territorialAuthority>
                           </author>
                        </approval>
                     </subjectOf>
                     <subjectOf>
                        <marketingAct>
                           <code code="C53292" codeSystem="2.16.840.1.113883.3.26.1.1"/>
                           <statusCode code="active"/>
                           <effectiveTime>
                              <low value="20170508"/>
                           </effectiveTime>
                        </marketingAct>
                     </subjectOf>
                     <subjectOf>
                        <characteristic classCode="OBS">
                           <code code="SPLCOLOR" codeSystem="2.16.840.1.113883.1.11.19255"/>
                           <value code="C48325" codeSystem="2.16.840.1.113883.3.26.1.1" displayName="white" xsi:type="CE">
                              <originalText/>
                           </value>
                        </characteristic>
                     </subjectOf>
                     <subjectOf>
                        <characteristic classCode="OBS">
                           <code code="SPLSHAPE" codeSystem="2.16.840.1.113883.1.11.19255"/>
                           <value code="C48336" codeSystem="2.16.840.1.113883.3.26.1.1" displayName="CAPSULE" xsi:type="CE">
                              <originalText/>
                           </value>
                        </characteristic>
                     </subjectOf>
                     <subjectOf>
                        <characteristic classCode="OBS">
                           <code code="SPLSIZE" codeSystem="2.16.840.1.113883.1.11.19255"/>
                           <value unit="mm" value="15" xsi:type="PQ"/>
                        </characteristic>
                     </subjectOf>
                     <subjectOf>
                        <characteristic classCode="OBS">
                           <code code="SPLSCORE" codeSystem="2.16.840.1.113883.1.11.19255"/>
                           <value value="1" xsi:type="INT"/>
                        </characteristic>
                     </subjectOf>
                     <subjectOf>
                        <characteristic classCode="OBS">
                           <code code="SPLIMPRINT" codeSystem="2.16.840.1.113883.1.11.19255"/>
                           <value xsi:type="ST">BI;05</value>
                        </characteristic>
                     </subjectOf>
                     <consumedIn>
                        <substanceAdministration>
                           <routeCode code="C38288" codeSystem="2.16.840.1.113883.3.26.1.1" displayName="ORAL"/>
                        </substanceAdministration>
                     </consumedIn>
                  </manufacturedProduct>
               </subject>
               <subject>
                  <manufacturedProduct>
                     <manufacturedProduct>
                        <code code="11788-007" codeSystem="2.16.840.1.113883.6.69"/>
                        <name>Ibuprofen</name>
                        <formCode code="C42931" codeSystem="2.16.840.1.113883.3.26.1.1" displayName="TABLET, FILM COATED"/>
                        <asEntityWithGeneric>
                           <genericMedicine>
                              <name>Ibuprofen</name>
                           </genericMedicine>
                        </asEntityWithGeneric>
                        <ingredient classCode="IACT">
                           <ingredientSubstance>
                              <code code="ETJ7Z6XBU4" codeSystem="2.16.840.1.113883.4.9"/>
                              <name>SILICON DIOXIDE</name>
                           </ingredientSubstance>
                        </ingredient>
                        <ingredient classCode="IACT">
                           <ingredientSubstance>
                              <code code="M28OL1HH48" codeSystem="2.16.840.1.113883.4.9"/>
                              <name>CROSCARMELLOSE SODIUM</name>
                           </ingredientSubstance>
                        </ingredient>
                        <ingredient classCode="IACT">
                           <ingredientSubstance>
                              <code code="L06K8R7DQK" codeSystem="2.16.840.1.113883.4.9"/>
                              <name>FD&amp;C BLUE NO. 2</name>
                           </ingredientSubstance>
                        </ingredient>
                        <ingredient classCode="IACT">
                           <ingredientSubstance>
                              <code code="I753WB2F1M" codeSystem="2.16.840.1.113883.4.9"/>
                              <name>FD&amp;C YELLOW NO. 5</name>
                           </ingredientSubstance>
                        </ingredient>
                        <ingredient classCode="IACT">
                           <ingredientSubstance>
                              <code code="H77VEI93A8" codeSystem="2.16.840.1.113883.4.9"/>
                              <name>FD&amp;C YELLOW NO. 6</name>
                           </ingredientSubstance>
                        </ingredient>
                        <ingredient classCode="IACT">
                           <ingredientSubstance>
                              <code code="1K09F3G675" codeSystem="2.16.840.1.113883.4.9"/>
                              <name>FERRIC OXIDE RED</name>
                           </ingredientSubstance>
                        </ingredient>
                        <ingredient classCode="IACT">
                           <ingredientSubstance>
                              <code code="1DI56QDM62" codeSystem="2.16.840.1.113883.4.9"/>
                              <name>LECITHIN, SOYBEAN</name>
                           </ingredientSubstance>
                        </ingredient>
                        <ingredient classCode="IACT">
                           <ingredientSubstance>
                              <code code="70097M6I30" codeSystem="2.16.840.1.113883.4.9"/>
                              <name>MAGNESIUM STEARATE</name>
                           </ingredientSubstance>
                        </ingredient>
                        <ingredient classCode="IACT">
                           <ingredientSubstance>
                              <code code="OP1R32D61U" codeSystem="2.16.840.1.113883.4.9"/>
                              <name>CELLULOSE, MICROCRYSTALLINE</name>
                           </ingredientSubstance>
                        </ingredient>
                        <ingredient classCode="IACT">
                           <ingredientSubstance>
                              <code code="4R4HFI6D95" codeSystem="2.16.840.1.113883.4.9"/>
                              <name>POLYETHYLENE GLYCOL 4000</name>
                           </ingredientSubstance>
                        </ingredient>
                        <ingredient classCode="IACT">
                           <ingredientSubstance>
                              <code code="532B59J990" codeSystem="2.16.840.1.113883.4.9"/>
                              <name>POLYVINYL ALCOHOL</name>
                           </ingredientSubstance>
                        </ingredient>
                        <ingredient classCode="IACT">
                           <ingredientSubstance>
                              <code code="O8232NY3SJ" codeSystem="2.16.840.1.113883.4.9"/>
                              <name>STARCH, PREGELATINIZED CORN</name>
                           </ingredientSubstance>
                        </ingredient>
                        <ingredient classCode="IACT">
                           <ingredientSubstance>
                              <code code="7SEV7J4R1U" codeSystem="2.16.840.1.113883.4.9"/>
                              <name>TALC</name>
                           </ingredientSubstance>
                        </ingredient>
                        <ingredient classCode="IACT">
                           <ingredientSubstance>
                              <code code="15FIX9V2JP" codeSystem="2.16.840.1.113883.4.9"/>
                              <name>TITANIUM DIOXIDE</name>
                           </ingredientSubstance>
                        </ingredient>
                        <ingredient classCode="ACTIB">
                           <quantity>
                              <numerator unit="mg" value="200"/>
                              <denominator unit="1" value="1"/>
                           </quantity>
                           <ingredientSubstance>
                              <code code="WK2XYI10QM" codeSystem="2.16.840.1.113883.4.9"/>
                              <name>IBUPROFEN</name>
                              <activeMoiety>
                                 <activeMoiety>
                                    <code code="WK2XYI10QM" codeSystem="2.16.840.1.113883.4.9"/>
                                    <name>IBUPROFEN</name>
                                 </activeMoiety>
                              </activeMoiety>
                           </ingredientSubstance>
                        </ingredient>
                        <asContent>
                           <quantity>
                              <numerator value="24" unit="1"/>
                              <denominator value="1"/>
                           </quantity>
                           <containerPackagedProduct>
                              <code/>
                              <formCode code="C43169" codeSystem="2.16.840.1.113883.3.26.1.1" displayName="BOTTLE"/>
                              <asContent>
                                 <quantity>
                                    <numerator value="1" unit="1"/>
                                    <denominator value="1"/>
                                 </quantity>
                                 <containerPackagedProduct>
                                    <code code="11788-007-07" codeSystem="2.16.840.1.113883.6.69"/>
                                    <formCode code="C43182" codeSystem="2.16.840.1.113883.3.26.1.1" displayName="CARTON"/>
                                 </containerPackagedProduct>
                                 <subjectOf>
                                    <marketingAct>
                                       <code code="C53292" codeSystem="2.16.840.1.113883.3.26.1.1"/>
                                       <statusCode code="active"/>
                                       <effectiveTime>
                                          <low value="20170508"/>
                                       </effectiveTime>
                                    </marketingAct>
                                 </subjectOf>
                              </asContent>
                           </containerPackagedProduct>
                           <subjectOf>
                              <characteristic>
                                 <code code="SPLCMBPRDTP" codeSystem="2.16.840.1.113883.1.11.19255"/>
                                 <value code="C112160" codeSystem="2.16.840.1.113883.3.26.1.1" displayName="Type 0: Not a Combination Product" xsi:type="CV"/>
                              </characteristic>
                           </subjectOf>
                        </asContent>
                        <asContent>
                           <quantity>
                              <numerator value="1000" unit="1"/>
                              <denominator value="1"/>
                           </quantity>
                           <containerPackagedProduct>
                              <code code="11788-007-10" codeSystem="2.16.840.1.113883.6.69"/>
                              <formCode code="C43169" codeSystem="2.16.840.1.113883.3.26.1.1" displayName="BOTTLE"/>
                           </containerPackagedProduct>
                           <subjectOf>
                              <characteristic>
                                 <code code="SPLCMBPRDTP" codeSystem="2.16.840.1.113883.1.11.19255"/>
                                 <value code="C112160" codeSystem="2.16.840.1.113883.3.26.1.1" displayName="Type 0: Not a Combination Product" xsi:type="CV"/>
                              </characteristic>
                           </subjectOf>
                           <subjectOf>
                              <marketingAct>
                                 <code code="C53292" codeSystem="2.16.840.1.113883.3.26.1.1"/>
                                 <statusCode code="active"/>
                                 <effectiveTime>
                                    <low value="20170508"/>
                                 </effectiveTime>
                              </marketingAct>
                           </subjectOf>
                        </asContent>
                     </manufacturedProduct>
                     <subjectOf>
                        <approval>
                           <id extension="ANDA207095" root="2.16.840.1.113883.3.150"/>
                           <code code="C73584" codeSystem="2.16.840.1.113883.3.26.1.1" displayName="ANDA"/>
                           <author>
                              <territorialAuthority>
                                 <territory>
                                    <code code="USA" codeSystem="2.16.840.1.113883.5.28"/>
                                 </territory>
                              </territorialAuthority>
                           </author>
                        </approval>
                     </subjectOf>
                     <subjectOf>
                        <marketingAct>
                           <code code="C53292" codeSystem="2.16.840.1.113883.3.26.1.1"/>
                           <statusCode code="active"/>
                           <effectiveTime>
                              <low value="20170508"/>
                           </effectiveTime>
                        </marketingAct>
                     </subjectOf>
                     <subjectOf>
                        <characteristic classCode="OBS">
                           <code code="SPLCOLOR" codeSystem="2.16.840.1.113883.1.11.19255"/>
                           <value code="C48332" codeSystem="2.16.840.1.113883.3.26.1.1" displayName="brown" xsi:type="CE">
                              <originalText/>
                           </value>
                        </characteristic>
                     </subjectOf>
                     <subjectOf>
                        <characteristic classCode="OBS">
                           <code code="SPLSHAPE" codeSystem="2.16.840.1.113883.1.11.19255"/>
                           <value code="C48336" codeSystem="2.16.840.1.113883.3.26.1.1" displayName="CAPSULE" xsi:type="CE">
                              <originalText/>
                           </value>
                        </characteristic>
                     </subjectOf>
                     <subjectOf>
                        <characteristic classCode="OBS">
                           <code code="SPLSIZE" codeSystem="2.16.840.1.113883.1.11.19255"/>
                           <value unit="mm" value="15" xsi:type="PQ"/>
                        </characteristic>
                     </subjectOf>
                     <subjectOf>
                        <characteristic classCode="OBS">
                           <code code="SPLSCORE" codeSystem="2.16.840.1.113883.1.11.19255"/>
                           <value value="1" xsi:type="INT"/>
                        </characteristic>
                     </subjectOf>
                     <subjectOf>
                        <characteristic classCode="OBS">
                           <code code="SPLIMPRINT" codeSystem="2.16.840.1.113883.1.11.19255"/>
                           <value xsi:type="ST">BI;07</value>
                        </characteristic>
                     </subjectOf>
                     <consumedIn>
                        <substanceAdministration>
                           <routeCode code="C38288" codeSystem="2.16.840.1.113883.3.26.1.1" displayName="ORAL"/>
                        </substanceAdministration>
                     </consumedIn>
                  </manufacturedProduct>
               </subject>
            </section>
         </component>
         <component>
            <section ID="Lb2b020b8-44cf-4c46-9276-8846e4d0c71c">
               <id root="5bd8cf4a-096b-5a2a-e053-2a91aa0ad499"/>
               <code code="42229-5" codeSystem="2.16.840.1.113883.6.1" displayName="SPL UNCLASSIFIED SECTION"/>
               <title>Important</title>
               <text>
                  <paragraph>Read all product information before using. Keep this box for important information.</paragraph>
               </text>
               <effectiveTime value="20151007"/>
            </section>
         </component>
         <component>
            <section ID="L8fd5d4d5-ed3e-4c17-8610-31b1b3f473ec">
               <id root="5bd8cf4a-096c-5a2a-e053-2a91aa0ad499"/>
               <code code="42229-5" codeSystem="2.16.840.1.113883.6.1" displayName="SPL UNCLASSIFIED SECTION"/>
               <title/>
               <text>
                  <paragraph>
                     <content styleCode="bold">
                        <content styleCode="italics">Drug Facts</content>
                     </content>
                  </paragraph>
               </text>
               <effectiveTime value="20151007"/>
            </section>
         </component>
         <component>
            <section ID="Lbb082f40-0c33-41ae-9ed6-88eec32122ca">
               <id root="5bd8cf4a-096d-5a2a-e053-2a91aa0ad499"/>
               <code code="55106-9" codeSystem="2.16.840.1.113883.6.1" displayName="OTC - ACTIVE INGREDIENT SECTION"/>
               <title>Active ingredient (in each caplet)</title>
               <text>
                  <paragraph>Ibuprofen 200 mg (NSAID)*</paragraph>
                  <paragraph>*nonsteroidal anti-inflammatory drug</paragraph>
               </text>
               <effectiveTime value="20140317"/>
            </section>
         </component>
         <component>
            <section ID="Lcbf9e814-fc51-4a0b-ba28-ada8c4ac7351">
               <id root="5bd8cf4a-096e-5a2a-e053-2a91aa0ad499"/>
               <code code="55105-1" codeSystem="2.16.840.1.113883.6.1" displayName="OTC - PURPOSE SECTION"/>
               <title>Purpose</title>
               <text>
                  <paragraph>Pain reliever/fever reducer</paragraph>
               </text>
               <effectiveTime value="20140317"/>
            </section>
         </component>
         <component>
            <section ID="Lfa22f0e2-c56e-4b0c-824d-6494eb512d8e">
               <id root="5bd8cf4a-096f-5a2a-e053-2a91aa0ad499"/>
               <code code="34067-9" codeSystem="2.16.840.1.113883.6.1" displayName="INDICATIONS &amp; USAGE SECTION"/>
               <title>Uses</title>
               <text>
                  <list listType="unordered">
                     <item>temporarily relieves minor aches and pains due to:
        
  
   <list listType="unordered" styleCode="Disc">
                           <item>headache</item>
                           <item>muscular aches</item>
                           <item>minor pain of arthritis</item>
                           <item>toothache</item>
                           <item>backache</item>
                           <item>the common cold</item>
                           <item>menstrual cramps</item>
                        </list>
                     </item>
                     <item>temporarily reduces fever</item>
                  </list>
                  <paragraph/>
               </text>
               <effectiveTime value="20140317"/>
            </section>
         </component>
         <component>
            <section ID="L08906cbd-92bc-4c5f-a278-64d1ff0a4237">
               <id root="5bd8cf4a-0970-5a2a-e053-2a91aa0ad499"/>
               <code code="34071-1" codeSystem="2.16.840.1.113883.6.1" displayName="WARNINGS SECTION"/>
               <title>Warnings</title>
               <text>
                  <paragraph/>
               </text>
               <effectiveTime value="20140317"/>
               <component>
                  <section ID="Lc6b48652-23a1-4c7f-a62d-877cf2eb9762">
                     <id root="5bd8cf4a-0971-5a2a-e053-2a91aa0ad499"/>
                     <code code="42229-5" codeSystem="2.16.840.1.113883.6.1" displayName="SPL UNCLASSIFIED SECTION"/>
                     <text>
                        <paragraph>
                           <content styleCode="bold">Allergy alert</content>
                        </paragraph>
                        <paragraph>Ibuprofen may cause a severe allergic reaction, especially in people allergic to aspirin. Symptoms may include:</paragraph>
                        <list listType="unordered">
                           <item>hives</item>
                           <item>facial swelling</item>
                           <item>asthma (wheezing)</item>
                           <item>shock</item>
                           <item>skin reddening</item>
                           <item>rash</item>
                           <item>blisters</item>
                        </list>
                        <paragraph>If an allergic reaction occurs, stop use and seek medical help right away.</paragraph>
                     </text>
                     <effectiveTime value="20140317"/>
                     <component>
                        <section ID="Ld8fd71fd-896f-49f0-81f9-34056018a81b">
                           <id root="5bd8cf4a-0972-5a2a-e053-2a91aa0ad499"/>
                           <code code="42229-5" codeSystem="2.16.840.1.113883.6.1" displayName="SPL UNCLASSIFIED SECTION"/>
                           <text>
                              <paragraph>
                                 <content styleCode="bold">Stomach bleeding warning:</content>
                              </paragraph>
                              <paragraph>This product contains an NSAID, which may cause severe stomach bleeding. The chance is higher if you:</paragraph>
                              <list listType="unordered">
                                 <item>are age 60 or older</item>
                                 <item>have had stomach ulcers or bleeding problems</item>
                                 <item>take a blood thinning (anticoagulant) or steroid drug</item>
                                 <item>take other drugs containing prescription or nonprescription NSAIDs (aspirin, ibuprofen, naproxen, or others)</item>
                                 <item>have 3 or more alcoholic drinks every day while using this product</item>
                                 <item>take more or for a longer time than directed</item>
                              </list>
                              <paragraph>
                                 <content styleCode="bold">Heart attack and stroke warning:</content>
                              </paragraph>
                              <paragraph>NSAIDs, except aspirin, increase the risk of heart attack, heart failure, and stroke. These can be fatal. The risk is higher if you use more than directed or for longer than directed.</paragraph>
                              <paragraph>
                                 <content styleCode="bold">Brown Film-Coated Caplets contain FD+C Yellow No. 5 (tartrazine) as a color additive</content>
                              </paragraph>
                           </text>
                           <effectiveTime value="20140317"/>
                           <component>
                              <section ID="L357f9bcd-80c0-4aad-82ba-cabd32e95dc6">
                                 <id root="5bd8cf4a-0973-5a2a-e053-2a91aa0ad499"/>
                                 <code code="50570-1" codeSystem="2.16.840.1.113883.6.1" displayName="OTC - DO NOT USE SECTION"/>
                                 <text>
                                    <paragraph>
                                       <content styleCode="bold">Do not use</content>
                                    </paragraph>
                                    <list listType="unordered">
                                       <item>if you have ever had an allergic reaction to ibuprofen or any other pain reliever/fever reducer</item>
                                       <item>right before or after heart surgery</item>
                                    </list>
                                 </text>
                                 <effectiveTime value="20140317"/>
                                 <component>
                                    <section ID="Lfd7b63fd-220f-4b18-a187-09126ab34916">
                                       <id root="5bd8cf4a-0974-5a2a-e053-2a91aa0ad499"/>
                                       <code code="50569-3" codeSystem="2.16.840.1.113883.6.1" displayName="OTC - ASK DOCTOR SECTION"/>
                                       <text>
                                          <paragraph>
                                             <content styleCode="bold">Ask a doctor before use if</content>
                                          </paragraph>
                                          <list listType="unordered">
                                             <item>you have problems or serious side effects from taking pain relievers or fever reducers</item>
                                             <item>the stomach bleeding warning applies to you</item>
                                             <item>you have a history of stomach problems, such as heartburn</item>
                                             <item>you have high blood pressure, heart disease, liver cirrhosis, kidney disease, asthma, or had a stroke</item>
                                             <item>you are taking a diuretic</item>
                                          </list>
                                       </text>
                                       <effectiveTime value="20140317"/>
                                       <component>
                                          <section ID="Lfcd0083c-843b-47f9-a17c-95e00042596e">
                                             <id root="5bd8cf4a-0975-5a2a-e053-2a91aa0ad499"/>
                                             <code code="50568-5" codeSystem="2.16.840.1.113883.6.1" displayName="OTC - ASK DOCTOR/PHARMACIST SECTION"/>
                                             <text>
                                                <paragraph>
                                                   <content styleCode="bold">Ask a doctor or pharmacist before use if you are</content>
                                                </paragraph>
                                                <list listType="unordered">
                                                   <item>taking aspirin for heart attack or stroke, because ibuprofen may decrease this benefit of aspirin</item>
                                                   <item>under a doctor's care for any serious condition</item>
                                                   <item>taking any other drug</item>
                                                </list>
                                             </text>
                                             <effectiveTime value="20140317"/>
                                             <component>
                                                <section ID="Le74d5f94-dfbf-4a1c-a7be-b91a73bfc081">
                                                   <id root="5bd8cf4a-0976-5a2a-e053-2a91aa0ad499"/>
                                                   <code code="50567-7" codeSystem="2.16.840.1.113883.6.1" displayName="OTC - WHEN USING SECTION"/>
                                                   <text>
                                                      <paragraph>
                                                         <content styleCode="bold">When using this product</content>
                                                      </paragraph>
                                                      <list listType="unordered">
                                                         <item>take with food or milk if stomach upset occurs</item>
                                                      </list>
                                                   </text>
                                                   <effectiveTime value="20140317"/>
                                                   <component>
                                                      <section ID="Le3d051a0-5f21-467f-8910-eaec169b73c7">
                                                         <id root="5bd8cf4a-0977-5a2a-e053-2a91aa0ad499"/>
                                                         <code code="50566-9" codeSystem="2.16.840.1.113883.6.1" displayName="OTC - STOP USE SECTION"/>
                                                         <text>
                                                            <paragraph>
                                                               <content styleCode="bold">Stop use and ask a doctor if</content>
                                                            </paragraph>
                                                            <list listType="unordered">
                                                               <item>you experience any of the following signs of stomach bleeding:
                      
  
   <list listType="unordered" styleCode="Disc">
                                                                     <item>feel faint</item>
                                                                     <item>vomit blood</item>
                                                                     <item>have bloody or black stools</item>
                                                                     <item>have stomach pain that does not get better</item>
                                                                  </list>
                                                               </item>
                                                               <item>you have symptoms of heart problems or stroke:
                      
  
   <list listType="unordered" styleCode="Disc">
                                                                     <item>chest pain</item>
                                                                     <item>trouble breathing</item>
                                                                     <item>weakness in one part or side of body</item>
                                                                     <item>slurred speech</item>
                                                                     <item>leg swelling</item>
                                                                  </list>
                                                               </item>
                                                               <item>pain gets worse or lasts more than 10 days</item>
                                                               <item>fever gets worse or lasts more than 3 days</item>
                                                               <item>redness or swelling is present in the painful area</item>
                                                               <item>any new symptoms appear</item>
                                                            </list>
                                                         </text>
                                                         <effectiveTime value="20140317"/>
                                                         <component>
                                                            <section ID="L329c0883-22c3-497b-a1a3-f66ebbb50bdb">
                                                               <id root="5bd8cf4a-0978-5a2a-e053-2a91aa0ad499"/>
                                                               <code code="53414-9" codeSystem="2.16.840.1.113883.6.1" displayName="OTC - PREGNANCY OR BREAST FEEDING SECTION"/>
                                                               <text>
                                                                  <paragraph>
                                                                     <content styleCode="bold">If pregnant or breast-feeding</content>, ask a health professional before use. It is especially important not to use ibuprofen during the last 3 months of pregnancy unless definitely directed to do so by a doctor because it may cause problems in the unborn child or complications during delivery.
                      

 </paragraph>
                                                               </text>
                                                               <effectiveTime value="20140317"/>
                                                               <component>
                                                                  <section ID="Ld5fb590b-7c24-4f52-a82f-d70fb544908f">
                                                                     <id root="5bd8cf4a-0979-5a2a-e053-2a91aa0ad499"/>
                                                                     <code code="50565-1" codeSystem="2.16.840.1.113883.6.1" displayName="OTC - KEEP OUT OF REACH OF CHILDREN SECTION"/>
                                                                     <text>
                                                                        <paragraph>
                                                                           <content styleCode="bold">Keep out of reach of children.</content>
                                                                        </paragraph>
                                                                        <paragraph>In case of overdose, get medical help or contact a Poison Control Center right away. (1-800-222-1222)</paragraph>
                                                                     </text>
                                                                     <effectiveTime value="20140317"/>
                                                                  </section>
                                                               </component>
                                                            </section>
                                                         </component>
                                                      </section>
                                                   </component>
                                                </section>
                                             </component>
                                          </section>
                                       </component>
                                    </section>
                                 </component>
                              </section>
                           </component>
                        </section>
                     </component>
                     <component>
                        <section ID="L3a0d7e1f-fe37-47b6-9386-c98fd98f398c">
                           <id root="5bd8cf4a-097a-5a2a-e053-2a91aa0ad499"/>
                           <code code="42229-5" codeSystem="2.16.840.1.113883.6.1" displayName="SPL UNCLASSIFIED SECTION"/>
                           <title/>
                           <text/>
                           <effectiveTime value="20160111"/>
                        </section>
                     </component>
                     <component>
                        <section ID="L9eed3f19-1132-4194-a33f-e27bfb14a993">
                           <id root="5bd8cf4a-097b-5a2a-e053-2a91aa0ad499"/>
                           <code code="42229-5" codeSystem="2.16.840.1.113883.6.1" displayName="SPL UNCLASSIFIED SECTION"/>
                           <title/>
                           <text/>
                           <effectiveTime value="20160111"/>
                        </section>
                     </component>
                  </section>
               </component>
            </section>
         </component>
         <component>
            <section ID="Leee5e99b-3429-444a-b214-50bf86b8e108">
               <id root="5bd8cf4a-097c-5a2a-e053-2a91aa0ad499"/>
               <code code="34068-7" codeSystem="2.16.840.1.113883.6.1" displayName="DOSAGE &amp; ADMINISTRATION SECTION"/>
               <title>Directions</title>
               <text>
                  <list listType="unordered">
                     <item>
                        <content styleCode="bold">do not take more than directed</content>
                     </item>
                     <item>
                        <content styleCode="bold">the smallest effective dose should be used</content>
                     </item>
                  </list>
                  <paragraph>
                     <content styleCode="bold">adults and children 12 years and older</content>
                  </paragraph>
                  <list listType="unordered">
                     <item>take 1caplet every 4 to 6 hours while symptoms persist</item>
                     <item>if pain or fever does not respond to 1 caplet, 2 caplets may be used</item>
                     <item>do not exceed 6 caplets in 24 hours, unless directed by a doctor</item>
                  </list>
                  <paragraph>
                     <content styleCode="bold">children under 12 years</content>
                  </paragraph>
                  <list listType="unordered">
                     <item>ask a doctor</item>
                  </list>
               </text>
               <effectiveTime value="20140317"/>
            </section>
         </component>
         <component>
            <section ID="Lf95fd60a-421e-4389-bf41-a5a17abfff5c">
               <id root="5bd8cf4a-097d-5a2a-e053-2a91aa0ad499"/>
               <code code="44425-7" codeSystem="2.16.840.1.113883.6.1" displayName="STORAGE AND HANDLING SECTION"/>
               <title>Other information</title>
               <text>
                  <list listType="unordered">
                     <item>store between 20-25C (68-77F)</item>
                     <item>
                        <content styleCode="bold">do not use if the inner seal imprinted with "SEALED for YOUR PROTECTION" is broken or missing</content>
                     </item>
                  </list>
               </text>
               <effectiveTime value="20140317"/>
            </section>
         </component>
         <component>
            <section ID="La5efcefe-5ff6-470c-8f34-5defd4550fa1">
               <id root="5bd8cf4a-097e-5a2a-e053-2a91aa0ad499"/>
               <code code="51727-6" codeSystem="2.16.840.1.113883.6.1" displayName="INACTIVE INGREDIENT SECTION"/>
               <title/>
               <text/>
               <effectiveTime value="20170426"/>
            </section>
         </component>
         <component>
            <section ID="Lbef786a9-1603-4cdd-845e-644ed40ccf9e">
               <id root="5bdae1da-8f8c-147b-e053-2a91aa0af597"/>
               <code code="53413-1" codeSystem="2.16.840.1.113883.6.1" displayName="OTC - QUESTIONS SECTION"/>
               <title>Questions or comments?</title>
               <text>
                  <paragraph>Call 
  <content styleCode="bold">1-844-374-0016 </content>Monday through Friday 9AM - 5PM EST.
 </paragraph>
               </text>
               <effectiveTime value="20140317"/>
            </section>
         </component>
         <component>
            <section ID="L1c4a3004-d1f0-4365-9ad4-512fdabde802">
               <id root="5bdae1da-8f90-147b-e053-2a91aa0af597"/>
               <code code="51945-4" codeSystem="2.16.840.1.113883.6.1" displayName="PACKAGE LABEL.PRINCIPAL DISPLAY PANEL"/>
               <text>
                  <paragraph>Ibuprofen tablets are available in the following colors and sizes:</paragraph>
                  <paragraph/>
                  <paragraph/>
                  <paragraph>
                     <content styleCode="bold">Orange, Capsule-shaped Tablet, debossed with BI 03</content>
                  </paragraph>
                  <paragraph>Bottles of 24 NDC 11788-003-07</paragraph>
                  <paragraph>Bottles of 1000 NDC 11788-003-10</paragraph>
                  <paragraph>
                     <renderMultiMedia referencedObject="img_5bdae1da-8f8d-147b-e053-2a91aa0af597"/>
                  </paragraph>
                  <paragraph/>
                  <paragraph/>
                  <paragraph/>
                  <paragraph>
                     <content styleCode="bold">White, Capsule-shaped Tablet, debossed with BI 05</content>
                  </paragraph>
                  <paragraph>Bottles of 24 NDC 11788-005-07</paragraph>
                  <paragraph>Bottles of 1000 NDC 11788-005-10</paragraph>
                  <paragraph>
                     <renderMultiMedia referencedObject="img_5bdae1da-8f8e-147b-e053-2a91aa0af597"/>
                  </paragraph>
                  <paragraph/>
                  <paragraph/>
                  <paragraph>
                     <content styleCode="bold">Brown, Capsule-shaped Tablet, debossed with BI 07</content>
                  </paragraph>
                  <paragraph>Bottles of 24 NDC 11788-007-07</paragraph>
                  <paragraph>Bottles of 1000 NDC 11788-007-10</paragraph>
                  <paragraph>
                     <renderMultiMedia referencedObject="img_5bdae1da-8f8f-147b-e053-2a91aa0af597"/>
                  </paragraph>
                  <paragraph/>
               </text>
               <effectiveTime value="20170330"/>
               <component>
                  <observationMedia ID="img_5bdae1da-8f8d-147b-e053-2a91aa0af597">
                     <text>orange</text>
                     <value mediaType="image/jpeg" xsi:type="ED">
                        <reference value="ibu 200 orange carton.jpg"/>
                     </value>
                  </observationMedia>
               </component>
               <component>
                  <observationMedia ID="img_5bdae1da-8f8e-147b-e053-2a91aa0af597">
                     <text>white</text>
                     <value mediaType="image/jpeg" xsi:type="ED">
                        <reference value="ibu 200 white carton.jpg"/>
                     </value>
                  </observationMedia>
               </component>
               <component>
                  <observationMedia ID="img_5bdae1da-8f8f-147b-e053-2a91aa0af597">
                     <text>brown</text>
                     <value mediaType="image/jpeg" xsi:type="ED">
                        <reference value="ibu 200 brown carton.jpg"/>
                     </value>
                  </observationMedia>
               </component>
            </section>
         </component>
      </structuredBody>
   </component>
</document>